Lgk/Help.py
Lgk/__init__.py
Lgk1-1.2.2.6.dist-info/LICENSE.py
Lgk1-1.2.2.6.dist-info/METADATA
Lgk1-1.2.2.6.dist-info/WHEEL
Lgk1-1.2.2.6.dist-info/top_level.txt
Lgk1-1.2.2.6.dist-info/RECORD
