Metadata-Version: 2.1
Name: Lgk1
Version: 1.2.2.6
Summary: Description: just write Lgk.Help.Help()
Home-page: UNKNOWN
Author: BT Ansixs
Author-email: noobra24l8w@gmail.com
License: LICENSE
Platform: UNKNOWN
License-File: LICENSE.py
